easypred/__init__.py
easypred/base_prediction.py
easypred/binary_prediction.py
easypred/binary_score.py
easypred/metrics.py
easypred/numeric_prediction.py
easypred/type_aliases.py
easypred/utils.py
easypred/tests/__init__.py
easypred/tests/test_aliases.py
easypred/tests/test_binary.py
easypred/tests/test_metrics.py
easypred/tests/test_numeric.py
easypred/tests/test_prediction.py
easypred/tests/test_score.py
easypred/tests/test_utils.py
easypred/tests/test_data/auc_breast.xlsx
easypred/tests/test_data/binary.xlsx
easypred-0.1.4.dist-info/LICENSE
easypred-0.1.4.dist-info/METADATA
easypred-0.1.4.dist-info/WHEEL
easypred-0.1.4.dist-info/top_level.txt
easypred-0.1.4.dist-info/RECORD
