Metadata-Version: 2.1
Name: easypred
Version: 0.1.4
Summary: Easily store, assess and compare predictions obtained through Machine Learning models.
Home-page: https://github.com/FilippoPisello/EasyPred
Author: Filippo Pisello
Author-email: filippo.pisello@live.it
License: MIT
Project-URL: Documentation, https://readthedocs.org/projects/easypred/
Platform: UNKNOWN
Classifier: License :: OSI Approved :: MIT License
Classifier: Programming Language :: Python :: 3
Classifier: Programming Language :: Python :: 3.7
Classifier: Programming Language :: Python :: 3.8
Classifier: Programming Language :: Python :: 3.9
Classifier: Programming Language :: Python :: 3.10
Classifier: Operating System :: OS Independent
Requires-Python: >=3.7
License-File: LICENSE
Requires-Dist: numpy (>=1.10)
Requires-Dist: pandas (>=1.1.0)
Requires-Dist: matplotlib (>=3.3)
